taktile_types/__init__.py
taktile_types/enums/__init__.py
taktile_types/enums/common.py
taktile_types/enums/deployment/__init__.py
taktile_types/enums/deployment/test.py
taktile_types/enums/endpoint.py
taktile_types/enums/http.py
taktile_types/enums/instance.py
taktile_types/enums/monitor.py
taktile_types/enums/repository/__init__.py
taktile_types/enums/repository/access.py
taktile_types/py.typed
taktile_types/schemas/__init__.py
taktile_types/schemas/deployment/__init__.py
taktile_types/schemas/deployment/endpoint.py
taktile_types/schemas/deployment/model.py
taktile_types/schemas/deployment/taktile_deployment.py
taktile_types/schemas/deployment/test.py
taktile_types/schemas/monitor.py
taktile_types/schemas/repository/__init__.py
taktile_types/schemas/repository/config_yaml.py
taktile_types/schemas/repository/pull_request.py
taktile_types/schemas/repository/repository.py
taktile_types/schemas/repository/resources.py
taktile_types/schemas/scope.py
taktile_types-0.22.0.dist-info/WHEEL
taktile_types-0.22.0.dist-info/METADATA
taktile_types-0.22.0.dist-info/RECORD
